tinygym/__init__.py
tinygym/main.py
tinygym/models.py
tinygym/utils.py
tinygym/envs/__init__.py
tinygym/envs/grid.c
tinygym/envs/grid.cpython-313-darwin.so
tinygym/envs/grid.pyx
tinygym/envs/multigrid.c
tinygym/envs/multigrid.cpython-313-darwin.so
tinygym/envs/multigrid.pyx
tinygym/envs/pong.c
tinygym/envs/pong.cpython-313-darwin.so
tinygym/envs/pong.pyx
tinygym-0.1.0.dist-info/METADATA
tinygym-0.1.0.dist-info/WHEEL
tinygym-0.1.0.dist-info/top_level.txt
tinygym-0.1.0.dist-info/RECORD
