Metadata-Version: 2.2
Name: tinygym
Version: 0.1.0
Summary: Reinforcement learning in tinygrad
Author-email: codingfisch <l_fisc17@wwu.de>
Requires-Dist: tinygrad
Requires-Dist: Cython
Requires-Dist: tqdm
Requires-Dist: plotille
Requires-Dist: tensorboard
